<?xml version="1.0" encoding="UTF-8"?>

<recipeml version="0.5">
  <recipe>
    <head>
      <title>(Machine) Doggie Biscuits</title>
      <categories>
        <cat>Dog biscuit</cat></categories>
      <yield>1</yield></head>
    <ingredients>
      <ing>
        <amt>
          <qty>3/4</qty>
          <unit>cups</unit></amt>
        <item>Hot water or meat juice</item></ing>
      <ing>
        <amt>
          <qty>1/3</qty>
          <unit>cups</unit></amt>
        <item>Margarine</item></ing>
      <ing>
        <amt>
          <qty>1/2</qty>
          <unit>cups</unit></amt>
        <item>Powdered milk</item></ing>
      <ing>
        <amt>
          <qty>1/2</qty>
          <unit>teaspoons</unit></amt>
        <item>Salt</item></ing>
      <ing>
        <amt>
          <qty>1</qty>
          <unit/></amt>
        <item>Egg, beaten</item></ing>
      <ing>
        <amt>
          <qty>3</qty>
          <unit>cups</unit></amt>
        <item>Whole wheat flour</item></ing></ingredients>
    <directions>
      <step>  Mix well - roll in to small logs in your hands and bake at 325 degrees for
  about 50 mins.
  
  This was posted by C.Harold Quinn (FPHK52A)
  
  File ftp://ftp.idiscover.co.uk/pub/food/mealmaster/recipes/mmdog.zip
 
</step></directions></recipe></recipeml>
